{
  "$schema": "https://ui.shadcn.com/schema/registry-item.json",
  "name": "animated-scroll-section-image-demo",
  "type": "registry:component",
  "title": "Animated Scroll Section with Image Demo",
  "description": "Demonstrating the use of the AnimatedScrollSection component with image.",
  "dependencies": [],
  "registryDependencies": ["@magicui/safari"],
  "devDependencies": [],
  "files": [
    {
      "path": "registry/demo/animated-scroll-section-image-demo/index.tsx",
      "type": "registry:component"
    }
  ]
}
